congrad/__init__.py
congrad/backend.py
congrad/backend_import_warn.py
congrad/cg_batch.py
congrad/cupy.py
congrad/monitoring.py
congrad/numpy.py
congrad/numpy_cupy.py
congrad/torch.py
congrad-0.0.5.dist-info/licenses/LICENSE
congrad-0.0.5.dist-info/METADATA
congrad-0.0.5.dist-info/WHEEL
congrad-0.0.5.dist-info/top_level.txt
congrad-0.0.5.dist-info/RECORD
