Metadata-Version: 2.4
Name: congrad
Version: 0.0.5
Summary: Generic conjugate gradient solver that works with your favorite backend
Author-email: "P. Michael Kielstra" <pmkielstra@math.berkeley.edu>
Project-URL: Homepage, https://github.com/PMKielstra/PyConGrad
Project-URL: Issues, https://github.com/PMKielstra/PyConGrad/issues
Classifier: Programming Language :: Python :: 3
Classifier: License :: CC0 1.0 Universal (CC0 1.0) Public Domain Dedication
Classifier: Operating System :: OS Independent
Requires-Python: >=3.8
License-File: LICENSE
Requires-Dist: tqdm
Provides-Extra: torch
Requires-Dist: torch; extra == "torch"
Provides-Extra: numpy
Requires-Dist: numpy; extra == "numpy"
Provides-Extra: cupy
Requires-Dist: cupy; extra == "cupy"
Dynamic: license-file
